keepachangelog/__init__.py
keepachangelog/__main__.py
keepachangelog/_changelog.py
keepachangelog/_versioning.py
keepachangelog/flask_restx.py
keepachangelog/starlette.py
keepachangelog/version.py
keepachangelog-2.0.0.dist-info/LICENSE
keepachangelog-2.0.0.dist-info/METADATA
keepachangelog-2.0.0.dist-info/WHEEL
keepachangelog-2.0.0.dist-info/entry_points.txt
keepachangelog-2.0.0.dist-info/top_level.txt
keepachangelog-2.0.0.dist-info/RECORD
