Metadata-Version: 2.1
Name: keepachangelog
Version: 2.0.0
Summary: Manipulate keep a changelog files
Author-email: Colin Bounouar <colin.bounouar.dev@gmail.com>
Maintainer-email: Colin Bounouar <colin.bounouar.dev@gmail.com>
License: MIT License
Project-URL: documentation, https://colin-b.github.io/keepachangelog/
Project-URL: repository, https://github.com/Colin-b/keepachangelog
Project-URL: changelog, https://github.com/Colin-b/keepachangelog/blob/master/CHANGELOG.md
Project-URL: issues, https://github.com/Colin-b/keepachangelog/issues
Keywords: changelog,CHANGELOG.md,markdown
Classifier: Development Status :: 5 - Production/Stable
Classifier: Intended Audience :: Developers
Classifier: License :: OSI Approved :: MIT License
Classifier: Natural Language :: English
Classifier: Typing :: Typed
Classifier: Programming Language :: Python
Classifier: Programming Language :: Python :: 3
Classifier: Programming Language :: Python :: 3.9
Classifier: Programming Language :: Python :: 3.10
Classifier: Programming Language :: Python :: 3.11
Classifier: Programming Language :: Python :: 3.12
Classifier: Topic :: Software Development :: Build Tools
Requires-Python: >=3.9
License-File: LICENSE
Provides-Extra: testing
Requires-Dist: httpx ==0.27.* ; extra == 'testing'
Requires-Dist: starlette ==0.37.* ; extra == 'testing'
Requires-Dist: flask-restx ==1.* ; extra == 'testing'
Requires-Dist: pytest-cov ==5.* ; extra == 'testing'
